odoo/addons/base_dav/README.rst
odoo/addons/base_dav/__init__.py
odoo/addons/base_dav/__manifest__.py
odoo/addons/base_dav/controllers/__init__.py
odoo/addons/base_dav/controllers/main.py
odoo/addons/base_dav/demo/dav_collection.xml
odoo/addons/base_dav/i18n/base_dav.pot
odoo/addons/base_dav/models/__init__.py
odoo/addons/base_dav/models/dav_collection.py
odoo/addons/base_dav/models/dav_collection_field_mapping.py
odoo/addons/base_dav/radicale/__init__.py
odoo/addons/base_dav/radicale/auth.py
odoo/addons/base_dav/radicale/collection.py
odoo/addons/base_dav/radicale/rights.py
odoo/addons/base_dav/readme/CONFIGURE.rst
odoo/addons/base_dav/readme/CONTRIBUTORS.rst
odoo/addons/base_dav/readme/CREDITS.rst
odoo/addons/base_dav/readme/DESCRIPTION.rst
odoo/addons/base_dav/readme/ROADMAP.rst
odoo/addons/base_dav/security/ir.model.access.csv
odoo/addons/base_dav/static/description/icon.png
odoo/addons/base_dav/static/description/index.html
odoo/addons/base_dav/tests/__init__.py
odoo/addons/base_dav/tests/test_base_dav.py
odoo/addons/base_dav/tests/test_collection.py
odoo/addons/base_dav/views/dav_collection.xml
odoo11_addon_base_dav-11.0.1.0.0.99.dev10.dist-info/METADATA
odoo11_addon_base_dav-11.0.1.0.0.99.dev10.dist-info/WHEEL
odoo11_addon_base_dav-11.0.1.0.0.99.dev10.dist-info/top_level.txt
odoo11_addon_base_dav-11.0.1.0.0.99.dev10.dist-info/RECORD
